{
  "groups": [
    { "id": "workbench", "name": "工作台", "icon": "home", "pageId": "workbench", "children": [] },
    { "id": "diseases", "name": "专科病种管理", "icon": "plus-square", "pageId": "diseases", "children": [] },
    { "id": "data-center", "name": "专科数据中心", "icon": "grid", "pageId": "data-center/datasets", "children": [
      { "id": "datasets", "name": "标准数据集管理", "pageId": "data-center/datasets" },
      { "id": "rdr", "name": "RDR 数据仓库", "pageId": "data-center/rdr" },
      { "id": "metadata", "name": "元数据管理", "pageId": "data-center/metadata" },
      { "id": "ai-governance", "name": "AI数据治理", "pageId": "data-center/ai" },
      { "id": "standards", "name": "医疗标准字典", "pageId": "data-center/standards" }
    ]},
    { "id": "knowledge", "name": "专科知识管理", "icon": "book", "pageId": "knowledge/disease", "children": [
      { "id": "disease-knowledge", "name": "疾病知识管理", "pageId": "knowledge/disease" },
      { "id": "knowledge-graph", "name": "AI知识图谱", "pageId": "knowledge/graph" },
      { "id": "contraindication", "name": "禁忌证清单", "pageId": "knowledge/contraindication" },
      { "id": "pre-consultation", "name": "专科预问诊问卷", "pageId": "patients/preconsult" }
    ]},
    { "id": "records", "name": "专科病历管理", "icon": "file-text", "pageId": "records/templates", "children": [
      { "id": "templates", "name": "病历模板管理", "pageId": "records/templates" },
      { "id": "scales", "name": "评估量表管理", "pageId": "records/scales" },
      { "id": "elements", "name": "专科数据元管理", "pageId": "records/elements" }
    ]},
    { "id": "pathways", "name": "专病诊疗路径", "icon": "git-branch", "pageId": "pathways/overview", "children": [
      { "id": "pathway-overview", "name": "诊疗路径总览", "pageId": "pathways/overview" },
      { "id": "pathway-manage", "name": "诊疗路径管理", "pageId": "pathways/manage" }
    ]},
    { "id": "ai", "name": "专科智能体管理", "icon": "cpu", "pageId": "ai/monitor", "children": [
      { "id": "ai-monitor", "name": "智能体运行监控", "pageId": "ai/monitor" }
    ]},
    { "id": "patients", "name": "患者管理中心", "icon": "users", "pageId": "patients/records", "children": [
      { "id": "records-folder", "name": "专科病历夹", "pageId": "patients/records" },
      { "id": "followup", "name": "患者随访管理", "pageId": "patients/followup" }
    ]},
    { "id": "quality", "name": "专科质控中心", "icon": "check-circle", "pageId": "quality/rules", "children": [
      { "id": "quality-rules", "name": "质控规则配置", "pageId": "quality/rules" },
      { "id": "quality-dispatch", "name": "质控规则分发", "pageId": "quality/dispatch" },
      { "id": "quality-dept", "name": "质控科室分发", "pageId": "quality/dept" },
      { "id": "record-quality", "name": "病历文书质控", "pageId": "quality/emr" },
      { "id": "disease-quality", "name": "单病种质控", "pageId": "quality/disease" },
      { "id": "time-quality", "name": "病种时效质控", "pageId": "quality/timeliness" }
    ]},
    { "id": "research", "name": "科研管理中心", "icon": "flask", "pageId": "research/overview", "children": [
      { "id": "research-overview", "name": "科研数据总览", "pageId": "research/overview" },
      { "id": "data-distribution", "name": "数据特征分布", "pageId": "research/distribution" },
      { "id": "research-review", "name": "科研数据审核", "pageId": "research/audit" },
      { "id": "research-data", "name": "科研数据管理", "pageId": "research/data" },
      { "id": "research-process", "name": "科研数据处理", "pageId": "research/process" },
      { "id": "cohort-manage", "name": "科研队列管理", "pageId": "research/cohort" },
      { "id": "crf-manage", "name": "CRF表单管理", "pageId": "research/crf" }
    ]}
  ]
}